pyplanc.cpython-311-darwin.so
pyplanc-0.0.2.dist-info/RECORD
pyplanc-0.0.2.dist-info/WHEEL
pyplanc-0.0.2.dist-info/METADATA
pyplanc-0.0.2.dist-info/licenses/license.md
pyplanc.dylibs/libnmflib.dylib
