Metadata-Version: 2.1
Name: pyplanc
Version: 0.0.2
Summary: Python bindings for the libplanc C++ library.
Author-Email: Andrew Robbins <andrew@robbinsa.me>, Yichen Wang <wayichen@umich.edu>, Joshua Welch <welchjd@umich.edu>, Ramakrishnan Kannan <kannanr@ornl.gov>
Maintainer-Email: Andrew Robbins <andrew@robbinsa.me>
License: # PLANC/pyPLANC/RcppPLANC - Parallel Low-rank Approximation with Nonnegativity Constraints
Classifier: Development Status :: 2 - Pre-Alpha
Classifier: License :: OSI Approved :: GNU General Public License v2 or later (GPLv2+)
Classifier: Programming Language :: Python :: 3 :: Only
Classifier: Programming Language :: Python :: 3.10
Classifier: Programming Language :: Python :: 3.11
Classifier: Programming Language :: Python :: 3.12
Classifier: Programming Language :: Python :: 3.13
Classifier: Programming Language :: C++
Classifier: Topic :: Scientific/Engineering :: Bio-Informatics
Classifier: Topic :: Scientific/Engineering :: Mathematics
Classifier: Operating System :: POSIX :: Linux
Classifier: Operating System :: Microsoft :: Windows
Classifier: Operating System :: MacOS :: MacOS X
Classifier: Intended Audience :: Science/Research
Project-URL: Homepage, https://welch-lab.github.io
Project-URL: GitHub, https://github.com/welch-lab/libplanc
Requires-Python: >=3.10
Requires-Dist: numpy<2.3,>=1.23.5
Requires-Dist: threadpoolctl<4.0,>=3.4.0
Requires-Dist: scipy>=1.12.0
Requires-Dist: progressbar2>=4.5.0
Provides-Extra: test
Requires-Dist: pytest>=6.0; extra == "test"
Requires-Dist: pyyaml>=6.0; extra == "test"
Provides-Extra: dev
Requires-Dist: ruff; extra == "dev"
